<launch>
  <arg name="input"/>
  <arg name="output"/>
  <arg name="node_name" default="detected_object_feature_remover"/>

  <load_composable_node target="pointcloud_container2">
    <composable_node pkg="detected_object_feature_remover" plugin="detected_object_feature_remover::DetectedObjectFeatureRemover" name="$(var node_name)" namespace="">
      <remap from="~/input" to="$(var input)"/>
      <remap from="~/output" to="$(var output)"/>
    </composable_node>
  </load_composable_node>
</launch>
